cheese_core/__init__.py
cheese_core/adb.py
cheese_core/app.py
cheese_core/assets.py
cheese_core/base.py
cheese_core/canvas.py
cheese_core/color.py
cheese_core/converters.py
cheese_core/device.py
cheese_core/env.py
cheese_core/events.py
cheese_core/files.py
cheese_core/floatingwindow.py
cheese_core/http.py
cheese_core/image.py
cheese_core/keyboard.py
cheese_core/keys.py
cheese_core/ocr.py
cheese_core/path.py
cheese_core/permissions.py
cheese_core/persistentstore.py
cheese_core/plugins.py
cheese_core/point.py
cheese_core/recordscreen.py
cheese_core/root.py
cheese_core/thread.py
cheese_core/toolwindow.py
cheese_core/uinode.py
cheese_core/websocket.py
cheese_core/webview.py
cheese_core/yolo.py
cheese_core/zip.py
java/__init__.py
java/dynamic_proxy.py
java/jclass.py
cheese_core-0.0.1.dist-info/METADATA
cheese_core-0.0.1.dist-info/WHEEL
cheese_core-0.0.1.dist-info/top_level.txt
cheese_core-0.0.1.dist-info/RECORD
